{
    "0": {
        "Lonavala": "27.00",
        "Mumbai": "27.00",
        "Pune": "21.19",
        "count": 0,
        "key": "SN378MZD",
        "timestamp": "2018-07-16 00:47:19.683131"
    },
    "1": {
        "Lonavala": "27.00",
        "Mumbai": "27.00",
        "Pune": "21.19",
        "count": 1,
        "key": "8KW5LOWU",
        "timestamp": "2018-07-16 00:47:22.125089"
    }
},
{
    "0": {
        "Lonavala": "28.00",
        "Mumbai": "28.00",
        "Pune": "22.16",
        "count": 0,
        "key": "W9NUXEPJ",
        "timestamp": "2018-07-18 23:39:12.270855"
    },
    "1": {
        "Lonavala": "28.00",
        "Mumbai": "28.00",
        "Pune": "22.16",
        "count": 1,
        "key": "62VYAWTR",
        "timestamp": "2018-07-18 23:39:17.720145"
    }
}{
    "0": {
        "Lonavala": "30.00",
        "Mumbai": "29.50",
        "Pune": "24.23",
        "count": 0,
        "key": "XA1CWE5P",
        "timestamp": "2018-08-31 14:40:48.145762"
    },
    "1": {
        "Lonavala": "30.00",
        "Mumbai": "29.50",
        "Pune": "24.23",
        "count": 1,
        "key": "R286UO0W",
        "timestamp": "2018-08-31 14:40:51.261751"
    }
}